cumulus_library_loinc/__init__.py
cumulus_library_loinc/loinc_builder.py
cumulus_library_loinc/manifest.toml
cumulus_library_loinc-0.1.0.dist-info/licenses/LICENSE
cumulus_library_loinc-0.1.0.dist-info/WHEEL
cumulus_library_loinc-0.1.0.dist-info/METADATA
cumulus_library_loinc-0.1.0.dist-info/RECORD
