Metadata-Version: 2.4
Name: cumulus_library_loinc
Version: 0.1.0
Summary: A LOINC ontology study for the Cumulus project
Keywords: FHIR,SQL,Health Informatics
Requires-Python: >= 3.11
License-Expression: Apache-2.0 AND LicenseRef-Loinc
Classifier: Operating System :: OS Independent
Classifier: Programming Language :: Python :: 3
Classifier: Topic :: Software Development :: Libraries :: Python Modules
License-File: LICENSE
Requires-Dist: cumulus-library >= 5.1, <6.0
Requires-Dist: requests >= 2.28
Requires-Dist: platformdirs
Requires-Dist: ruff >= 0.14, < 0.15 ; extra == "dev"
Requires-Dist: pre-commit ; extra == "dev"
Requires-Dist: pytest ; extra == "test"
Requires-Dist: pytest-cov ; extra == "test"
Requires-Dist: responses ; extra == "test"
Project-URL: Documentation, https://docs.smarthealthit.org/cumulus/
Project-URL: Home, https://smarthealthit.org/cumulus
Project-URL: Source, https://github.com/smart-on-fhir/cumulus-library-loinc
Provides-Extra: dev
Provides-Extra: test
